{
  "posts": [
    {
      "id": 8,
      "name": "Jahir Uddin",
      "gender": "Male",
      "hobby": "Coding"
    },
    {
      "id": 10,
      "name": "Masud Rana",
      "gender": "Male",
      "hobby": [
        "Reading",
        "Fashing",
        "Sleeping"
      ]
    },
    {
      "id": 11,
      "name": "Shohab vai ",
      "gender": "Male",
      "hobby": [
        "Gaming"
      ]
    },
    {
      "id": 12,
      "name": "ajhi",
      "gender": "Male",
      "hobby": [
        "Fashing",
        "Sleeping"
      ]
    }
  ],
  "comments": [],
  "profile": {
    "name": "typicode"
  }
}